bgg_api-1.1.15.dist-info/licenses/AUTHORS.md
bgg_api-1.1.15.dist-info/licenses/LICENSE
boardgamegeek/__init__.py
boardgamegeek/api.py
boardgamegeek/cache.py
boardgamegeek/exceptions.py
boardgamegeek/legacy_api.py
boardgamegeek/main.py
boardgamegeek/utils.py
boardgamegeek/loaders/__init__.py
boardgamegeek/loaders/collection.py
boardgamegeek/loaders/game.py
boardgamegeek/loaders/geeklist.py
boardgamegeek/loaders/guild.py
boardgamegeek/loaders/hotitems.py
boardgamegeek/loaders/plays.py
boardgamegeek/objects/__init__.py
boardgamegeek/objects/collection.py
boardgamegeek/objects/games.py
boardgamegeek/objects/geeklist.py
boardgamegeek/objects/guild.py
boardgamegeek/objects/hotitems.py
boardgamegeek/objects/plays.py
boardgamegeek/objects/search.py
boardgamegeek/objects/things.py
boardgamegeek/objects/user.py
bgg_api-1.1.15.dist-info/METADATA
bgg_api-1.1.15.dist-info/WHEEL
bgg_api-1.1.15.dist-info/entry_points.txt
bgg_api-1.1.15.dist-info/top_level.txt
bgg_api-1.1.15.dist-info/RECORD
