Metadata-Version: 2.4
Name: bgg-api
Version: 1.1.15
Summary: A Python API for boardgamegeek.com
Home-page: https://github.com/SukiCZ/boardgamegeek
Author: Jakub Boukal
Author-email: Jakub Boukal <www.bagr@gmail.com>
License: BSD
Project-URL: Homepage, https://github.com/SukiCZ/boardgamegeek
Project-URL: Documentation, https://bgg-api.readthedocs.io/en/latest/
Project-URL: Coverage, https://codecov.io/gh/SukiCZ/boardgamegeek
Keywords: boardgamegeek,bgg,boardgame,api
Classifier: Programming Language :: Python
Classifier: Programming Language :: Python :: 3.8
Classifier: Programming Language :: Python :: 3.9
Classifier: Programming Language :: Python :: 3.10
Classifier: Programming Language :: Python :: 3.11
Classifier: Programming Language :: Python :: 3.12
Classifier: Programming Language :: Python :: 3.13
Classifier: License :: OSI Approved :: BSD License
Classifier: Development Status :: 4 - Beta
Classifier: Operating System :: OS Independent
Classifier: Intended Audience :: Developers
Classifier: Topic :: Games/Entertainment :: Board Games
Classifier: Topic :: Internet :: WWW/HTTP :: Dynamic Content
Requires-Python: >=3.8
License-File: LICENSE
License-File: AUTHORS.md
Requires-Dist: requests<3.0.0,>=2.31.0
Requires-Dist: requests-cache<2.0.0,>=1.1.1
Dynamic: author
Dynamic: home-page
Dynamic: license-file
